{
  "version": "7",
  "dialect": "postgresql",
  "entries": [
    {
      "idx": 0,
      "version": "7",
      "when": 1770776437207,
      "tag": "0000_fair_the_executioner",
      "breakpoints": true
    },
    {
      "idx": 1,
      "version": "7",
      "when": 1770816866878,
      "tag": "0001_wandering_ted_forrester",
      "breakpoints": true
    },
    {
      "idx": 2,
      "version": "7",
      "when": 1771020698855,
      "tag": "0002_warm_the_executioner",
      "breakpoints": true
    },
    {
      "idx": 3,
      "version": "7",
      "when": 1771020800000,
      "tag": "0003_pgvector",
      "breakpoints": true
    }
  ]
}